{
    "Port8001Listening":  false,
    "MeetingPlannerRunning":  true,
    "StoreActivityDashboardRunning":  false,
    "Port5000Listening":  true,
    "VETDashboardRunning":  true,
    "TDARunning":  true,
    "RebootPending":  true,
    "DCTasksCount":  26,
    "Port8888Listening":  false,
    "ProjectsInStoresRunning":  false,
    "Port8090Listening":  true,
    "JobCodesRunning":  true,
    "TDAWeeklyEmailTask":  true,
    "ZorroRunning":  false,
    "Port5001Listening":  true,
    "RebootReasons":  "Pending file operations",
    "TimeStamp":  {
                      "value":  "\/Date(1776078015907)\/",
                      "DisplayHint":  2,
                      "DateTime":  "Monday, April 13, 2026 6:00:15 AM"
                  },
    "JobCodesBackendTask":  true,
    "Port8080Listening":  true
}
