[
  {
    "id": 1,
    "type": "update",
    "job_code": "71-76-624",
    "changes": {
      "SMART Job Code": "71-76-624",
      "Workday Job Code": "US-71-0076-000624",
      "Job Title": "Acad Coord  ",
      "Category": "Salary",
      "Workgroup": "Support",
      "Team": "Academy",
      "Job Family": "Specialty Supervisor",
      "PG Level": "SUP",
      "Supervisor?": "No",
      "Reports to Title": "Academy Lead",
      "Position Mgmt or Job Mgmt": "PM"
    },
    "reason": "This is a test.",
    "requested_by": "krush",
    "requested_by_name": "Kendall Rush",
    "status": "pending",
    "submitted": "2026-01-22T12:39:00.783902"
  },
  {
    "id": 2,
    "type": "update",
    "job_code": "1-202-2104",
    "changes": {
      "SMART Job Code": "1-202-2104",
      "Workday Job Code": "US-01-0202-002104",
      "Job Title": "Adult Beverage DM ",
      "Category": "Salary",
      "Workgroup": "Food & Consumables",
      "Team": "Food/Consumables",
      "Job Family": "Specialty Supervisor",
      "PG Level": "TL2",
      "Supervisor?": "Yes",
      "Reports to Title": "Food & Consumables Coach",
      "Position Mgmt or Job Mgmt": "PM"
    },
    "reason": "test",
    "requested_by": "krush",
    "requested_by_name": "Kendall Rush",
    "status": "pending",
    "submitted": "2026-01-22T13:00:35.698523"
  },
  {
    "id": 3,
    "type": "update",
    "job_code": "1-615-7410",
    "changes": {
      "SMART Job Code": "1-615-7410",
      "Workday Job Code": "US-01-0615-007410",
      "Job Title": "Adult Beverage TA",
      "Category": "Hourly",
      "Workgroup": "Food & Consumables",
      "Team": "Food/Consumables",
      "Job Family": "Team Associate",
      "PG Level": "C",
      "Supervisor?": "No",
      "Reports to Title": "",
      "Position Mgmt or Job Mgmt": "JM"
    },
    "reason": "test",
    "requested_by": "krush",
    "requested_by_name": "Kendall Rush",
    "status": "rejected",
    "submitted": "2026-01-22T13:01:01.797328",
    "rejected_by": "krush",
    "rejected_by_name": "Kendall Rush",
    "rejected_date": "2026-01-28T12:12:06.314650",
    "rejection_reason": "This was a test."
  },
  {
    "id": 4,
    "type": "update",
    "job_code": "1-996-754",
    "changes": {
      "SMART Job Code": "1-996-754",
      "Workday Job Code": "US-01-0996-000754",
      "Job Title": "AP Investigator",
      "Category": "Salary",
      "Workgroup": "Asset Protection",
      "Team": "Asset Protection",
      "Job Family": "Specialty Supervisor",
      "PG Level": "SUP",
      "Supervisor?": "No",
      "Reports to Title": "AP Coach",
      "Position Mgmt or Job Mgmt": "PM"
    },
    "reason": "Test - change Category",
    "requested_by": "krush",
    "requested_by_name": "Kendall Rush",
    "status": "pending",
    "submitted": "2026-01-28T12:20:57.267800"
  },
  {
    "id": 5,
    "type": "update",
    "job_code": "1-600-7200",
    "changes": {
      "SMART Job Code": "1-600-7200",
      "Workday Job Code": "US-01-0600-007200",
      "Job Title": "Meat/Produce TL 1-600-7200",
      "Category": "Salary",
      "Workgroup": "Food & Consumables",
      "Team": "Meat/Produce",
      "Job Family": "Team Lead",
      "PG Level": "TL2",
      "Supervisor?": "Yes",
      "Reports to Title": "Food & Consumables Coach",
      "Position Mgmt or Job Mgmt": "PM"
    },
    "previous_values": {
      "SMART Job Code": "1-600-7200",
      "Workday Job Code": "US-01-0600-007200",
      "Job Title": "Meat/Produce TL 1-600-7200",
      "Category": "Hourly",
      "Workgroup": "Food & Consumables",
      "Team": "Meat/Produce",
      "Job Family": "Team Lead",
      "PG Level": "TL2",
      "Supervisor?": "Yes",
      "Reports to Title": "Food & Consumables Coach",
      "Position Mgmt or Job Mgmt": "PM"
    },
    "reason": "test",
    "requested_by": "krush",
    "requested_by_name": "Kendall Rush",
    "status": "pending",
    "submitted": "2026-01-28T14:25:06.814938"
  }
]